jedopo/__init__.py
jedopo/poc.py
jedopo_py-0.0.1.dist-info/LICENSE.md
jedopo_py-0.0.1.dist-info/METADATA
jedopo_py-0.0.1.dist-info/WHEEL
jedopo_py-0.0.1.dist-info/top_level.txt
jedopo_py-0.0.1.dist-info/RECORD
